byted_rtc_assessment_meego_tools/__init__.py
byted_rtc_assessment_meego_tools-0.0.1.dist-info/METADATA
byted_rtc_assessment_meego_tools-0.0.1.dist-info/WHEEL
byted_rtc_assessment_meego_tools-0.0.1.dist-info/top_level.txt
byted_rtc_assessment_meego_tools-0.0.1.dist-info/RECORD
