Metadata-Version: 2.1
Name: byted-rtc-assessment-meego-tools
Version: 0.0.1
Summary: A simple package named byted_rtc_assessment_meego_tools
Home-page: https://github.com/artifact/byted_rtc_assessment_meego_tools.git
Author: artifact
Author-email: artifact@example.com
License: UNKNOWN
Platform: UNKNOWN
Classifier: Programming Language :: Python :: 3
Classifier: License :: OSI Approved :: MIT License
Classifier: Operating System :: OS Independent
